README.md
setup.cfg
setup.py
Stock_Analysis/Stock.py
Stock_Analysis/__init__.py
Stock_Analysis/api.py
Stock_Analysis/test.py
Summer_Project.egg-info/PKG-INFO
Summer_Project.egg-info/SOURCES.txt
Summer_Project.egg-info/dependency_links.txt
Summer_Project.egg-info/top_level.txt