Metadata-Version: 2.1
Name: Summer-Project
Version: 2.0
Summary: Summer Project
Home-page: https://github.com/ARU300/SummerProject/archive/2.0.zip
Author: ARU300
Author-email: ath.projalph@gmail.com
License: UNKNOWN
Keywords: Machine Learning,Python3
Platform: UNKNOWN
